Metadata-Version: 2.1
Name: fileUts
Version: 0.0.2
Summary: File and path manager package
Home-page: UNKNOWN
Author: Melque Lima
Author-email: melque_ex@yahoo.com.br
License: MIT
Keywords: fileUts
Platform: UNKNOWN
Classifier: Development Status :: 5 - Production/Stable
Classifier: Intended Audience :: Education
Classifier: Operating System :: Microsoft :: Windows :: Windows 10
Classifier: License :: OSI Approved :: MIT License
Classifier: Programming Language :: Python :: 3
